human_pose_estimator/__init__.py
human_pose_estimator/__main__.py
human_pose_estimator/image_reader.py
human_pose_estimator/pose_estimator.py
human_pose_estimator/train.py
human_pose_estimator/val.py
human_pose_estimator/video_reader.py
human_pose_estimator/datasets/__init__.py
human_pose_estimator/datasets/coco.py
human_pose_estimator/datasets/transformations.py
human_pose_estimator/models/__init__.py
human_pose_estimator/models/with_mobilenet.py
human_pose_estimator/modules/__init__.py
human_pose_estimator/modules/conv.py
human_pose_estimator/modules/get_parameters.py
human_pose_estimator/modules/keypoints.py
human_pose_estimator/modules/load_state.py
human_pose_estimator/modules/loss.py
human_pose_estimator/modules/one_euro_filter.py
human_pose_estimator/modules/pose.py
human_pose_estimator-1.0.0.dist-info/LICENSE
human_pose_estimator-1.0.0.dist-info/METADATA
human_pose_estimator-1.0.0.dist-info/WHEEL
human_pose_estimator-1.0.0.dist-info/entry_points.txt
human_pose_estimator-1.0.0.dist-info/top_level.txt
human_pose_estimator-1.0.0.dist-info/RECORD
