Metadata-Version: 2.1
Name: human-pose-estimator
Version: 1.0.0
Summary: Lightweight human pose estimation using pytorch
Home-page: https://github.com/Daniil-Osokin/lightweight-human-pose-estimation.pytorch
Author: Daniil-Osokin
Author-email: daniil.osokin@gmail.com
License: Apache
Classifier: Development Status :: 5 - Production/Stable
Classifier: Intended Audience :: Developers
Classifier: Intended Audience :: Science/Research
Classifier: Natural Language :: English
Classifier: Operating System :: OS Independent
Classifier: Programming Language :: Python
Classifier: Programming Language :: Python :: 3.5
Classifier: Programming Language :: Python :: 3.6
Classifier: Programming Language :: Python :: 3.7
Classifier: Programming Language :: Python :: 3.8
Classifier: Programming Language :: Python :: 3.9
Classifier: Programming Language :: Python :: 3 :: Only
License-File: LICENSE
Requires-Dist: torch >=0.4.1
Requires-Dist: torchvision >=0.2.1
Requires-Dist: pycocotools ==2.0.7
Requires-Dist: opencv-python >=3.4.0.14
Requires-Dist: numpy >=1.14.0
Requires-Dist: filetype >=1.2.0
